MANIFEST.in
README.rst
__init__.py
abbrev.py
bayes_classifier.py
bayesian_classifier2.py
bayesian_classifier_nltk.py
bibreview
command_line.py
complement_naive_bayes.py
export_bibtex.py
globdef.py
gui.py
kfeatures.py
model.py
neural_network.py
parse_bibreview.py
parse_bibtex.py
parse_pubmed.py
parse_reflib.py
princomp.py
run_bibreview_windows.py
setup.cfg
setup.py
test.py
./__init__.py
./abbrev.py
./bayes_classifier.py
./bayesian_classifier2.py
./bayesian_classifier_nltk.py
./command_line.py
./complement_naive_bayes.py
./export_bibtex.py
./globdef.py
./gui.py
./kfeatures.py
./model.py
./neural_network.py
./parse_bibreview.py
./parse_bibtex.py
./parse_pubmed.py
./parse_reflib.py
./princomp.py
./run_bibreview_windows.py
./test.py
./data/-1.png
./data/-1.svg
./data/0.png
./data/0.svg
./data/1.png
./data/1.svg
./data/abbrev.txt
./data/article.png
./data/article.svg
./data/base.png
./data/base.svg
./data/book.png
./data/book.svg
./data/c-10.png
./data/c-10.svg
./data/c-101.png
./data/c-101.svg
./data/c-11.png
./data/c-11.svg
./data/c.png
./data/c.svg
./data/c01.png
./data/c01.svg
./data/conference.png
./data/conference.svg
./data/in_book.png
./data/in_book.svg
./data/phd.png
./data/phd.svg
./data/tag.png
./data/tag.svg
./data/website.png
./data/website.svg
./locale/en
./locale/fr
./locale/en/LC_MESSAGES
./locale/en/LC_MESSAGES/bibreview.mo
./locale/fr/LC_MESSAGES
./locale/fr/LC_MESSAGES/bibreview.mo
BibReview.egg-info/PKG-INFO
BibReview.egg-info/SOURCES.txt
BibReview.egg-info/dependency_links.txt
BibReview.egg-info/not-zip-safe
BibReview.egg-info/top_level.txt
data/-1.png
data/-1.svg
data/0.png
data/0.svg
data/1.png
data/1.svg
data/abbrev.txt
data/article.png
data/article.svg
data/base.png
data/base.svg
data/book.png
data/book.svg
data/c-10.png
data/c-10.svg
data/c-101.png
data/c-101.svg
data/c-11.png
data/c-11.svg
data/c.png
data/c.svg
data/c01.png
data/c01.svg
data/conference.png
data/conference.svg
data/in_book.png
data/in_book.svg
data/phd.png
data/phd.svg
data/tag.png
data/tag.svg
data/website.png
data/website.svg
doc/bibreview_fr.png
doc/doc_fr.lyx
doc/doc_fr.pdf
doc/yb_aide_decision.py
doc/yb_s4.py
doc/yb_test.py
