Metadata-Version: 1.1
Name: BibReview
Version: 0.2.4
Summary: BibReview is a software for managing bibliographic database. It includes avanced functions for literature reviews.
Home-page: http://www.lesfleursdunormal.fr/static/informatique/bibreview/index_fr.html
Author: Lamy Jean-Baptiste (Jiba)
Author-email: <jibalamy *@* free *.* fr>
License: GPLv3+
Platform: UNKNOWN
Classifier: Development Status :: 4 - Beta
Classifier: Programming Language :: Python :: 2
Classifier: License :: OSI Approved :: GNU General Public License v3 or later (GPLv3+)
Classifier: Environment :: X11 Applications :: GTK
Classifier: Intended Audience :: Science/Research
Classifier: Operating System :: POSIX :: Linux
Requires: pygtk
Requires: editobj2
